README.md
setup.py
PyTreasuryDirect.egg-info/PKG-INFO
PyTreasuryDirect.egg-info/SOURCES.txt
PyTreasuryDirect.egg-info/dependency_links.txt
PyTreasuryDirect.egg-info/requires.txt
PyTreasuryDirect.egg-info/top_level.txt
PyTreasuryDirect.egg-info/zip-safe
pytreasurydirect/__init__.py
pytreasurydirect/pytreasurydirect.py