Metadata-Version: 1.0
Name: PyTreasuryDirect
Version: 0.1.1
Summary: A Python wrapper for the Treasury Direct API
Home-page: https://github.com/npezolano/PyTreasuryDirect
Author: Nicholas Pezolano
Author-email: npezolano@gmail.com
License: MIT
Platform: UNKNOWN
